{
  "version": "6",
  "dialect": "sqlite",
  "entries": [
    {
      "idx": 0,
      "version": "6",
      "when": 1716540437848,
      "tag": "0000_init_db",
      "breakpoints": true
    },
    {
      "idx": 1,
      "version": "6",
      "when": 1716542217208,
      "tag": "0001_primary_keys",
      "breakpoints": true
    },
    {
      "idx": 2,
      "version": "6",
      "when": 1716542320843,
      "tag": "0002_one-to-one",
      "breakpoints": true
    },
    {
      "idx": 3,
      "version": "6",
      "when": 1716542429108,
      "tag": "0003_t",
      "breakpoints": true
    },
    {
      "idx": 4,
      "version": "6",
      "when": 1716543204397,
      "tag": "0004_t",
      "breakpoints": true
    },
    {
      "idx": 5,
      "version": "6",
      "when": 1716543598176,
      "tag": "0005_t",
      "breakpoints": true
    },
    {
      "idx": 6,
      "version": "6",
      "when": 1716543630897,
      "tag": "0006_t",
      "breakpoints": true
    }
  ]
}